tubein/TubeIn.py
tubein/__init__.py
tubein/__main__.py
tubein/utils.py
tubein-0.0.8.dist-info/LICENSE.txt
tubein-0.0.8.dist-info/METADATA
tubein-0.0.8.dist-info/WHEEL
tubein-0.0.8.dist-info/entry_points.txt
tubein-0.0.8.dist-info/top_level.txt
tubein-0.0.8.dist-info/RECORD
