Metadata-Version: 2.1
Name: tubein
Version: 0.0.8
Summary: a VOD service to altCensored.com uploader based on tubeup
Author-email: admin altCensored <admin@altCensored.com>
Project-URL: Homepage, https://github.com/altCensored/tubein
Project-URL: Issues, https://github.com/altCensored/tubein/issues
Requires-Python: >=3.8
License-File: LICENSE.txt
Requires-Dist: internetarchive
Requires-Dist: docopt
Requires-Dist: yt-dlp
Requires-Dist: minio
